[
  {
    "NODE_ID": 0,
    "TYPE": "STOP",
    "STOP_ID": 312101781,
    "LAT": 35.92929823,
    "LNG": 127.16083438
  },
  {
    "NODE_ID": 1,
    "TYPE": "INTERMEDIATE",
    "LAT": 35.92825137748596,
    "LNG": 127.16199641146483
  },
  {
    "NODE_ID": 2,
    "TYPE": "STOP",
    "STOP_ID": 312101774,
    "LAT": 35.92787194,
    "LNG": 127.16234212
  },
  {
    "NODE_ID": 3,
    "TYPE": "INTERMEDIATE",
    "LAT": 35.926999199841035,
    "LNG": 127.16343975094397
  },
  {
    "NODE_ID": 4,
    "TYPE": "INTERMEDIATE",
    "LAT": 35.92595274193345,
    "LNG": 127.16486624561229
  },
  {
    "NODE_ID": 5,
    "TYPE": "STOP",
    "STOP_ID": 312101766,
    "LAT": 35.92709592,
    "LNG": 127.16602905
  },
  {
    "NODE_ID": 6,
    "TYPE": "INTERMEDIATE",
    "LAT": 35.92737033252194,
    "LNG": 127.16620757212941
  },
  {
    "NODE_ID": 7,
    "TYPE": "INTERMEDIATE",
    "LAT": 35.928831590743336,
    "LNG": 127.16748291569125
  },
  {
    "NODE_ID": 8,
    "TYPE": "INTERMEDIATE",
    "LAT": 35.930447928064154,
    "LNG": 127.16833941337721
  },
  {
    "NODE_ID": 9,
    "TYPE": "STOP",
    "STOP_ID": 312101793,
    "LAT": 35.9320858,
    "LNG": 127.1686913
  },
  {
    "NODE_ID": 10,
    "TYPE": "INTERMEDIATE",
    "LAT": 35.93219038238984,
    "LNG": 127.16868323696613
  },
  {
    "NODE_ID": 11,
    "TYPE": "INTERMEDIATE",
    "LAT": 35.93396076755885,
    "LNG": 127.1686069069079
  },
  {
    "NODE_ID": 12,
    "TYPE": "INTERMEDIATE",
    "LAT": 35.93574735329576,
    "LNG": 127.16847816168011
  },
  {
    "NODE_ID": 13,
    "TYPE": "INTERMEDIATE",
    "LAT": 35.93753443779903,
    "LNG": 127.16836083699187
  },
  {
    "NODE_ID": 14,
    "TYPE": "STOP",
    "STOP_ID": 312101819,
    "LAT": 35.9384139,
    "LNG": 127.16833496
  },
  {
    "NODE_ID": 15,
    "TYPE": "INTERMEDIATE",
    "LAT": 35.93927610179029,
    "LNG": 127.16813871613746
  },
  {
    "NODE_ID": 16,
    "TYPE": "STOP",
    "STOP_ID": 312101831,
    "LAT": 35.93974878,
    "LNG": 127.16746889
  },
  {
    "NODE_ID": 17,
    "TYPE": "INTERMEDIATE",
    "LAT": 35.94045245846623,
    "LNG": 127.16649775031458
  },
  {
    "NODE_ID": 18,
    "TYPE": "INTERMEDIATE",
    "LAT": 35.94139559099018,
    "LNG": 127.16668216588482
  },
  {
    "NODE_ID": 19,
    "TYPE": "STOP",
    "STOP_ID": 312101839,
    "LAT": 35.9419505,
    "LNG": 127.16867406
  },
  {
    "NODE_ID": 20,
    "TYPE": "INTERMEDIATE",
    "LAT": 35.94206139627457,
    "LNG": 127.1686276179532
  },
  {
    "NODE_ID": 21,
    "TYPE": "INTERMEDIATE",
    "LAT": 35.94187332630635,
    "LNG": 127.17056837398488
  },
  {
    "NODE_ID": 22,
    "TYPE": "INTERMEDIATE",
    "LAT": 35.940826479855204,
    "LNG": 127.17236115427195
  },
  {
    "NODE_ID": 23,
    "TYPE": "INTERMEDIATE",
    "LAT": 35.939650546226204,
    "LNG": 127.17390027263903
  },
  {
    "NODE_ID": 24,
    "TYPE": "INTERMEDIATE",
    "LAT": 35.93793391146346,
    "LNG": 127.17386122233523
  },
  {
    "NODE_ID": 25,
    "TYPE": "STOP",
    "STOP_ID": 312101818,
    "LAT": 35.93745423,
    "LNG": 127.17362441
  },
  {
    "NODE_ID": 26,
    "TYPE": "INTERMEDIATE",
    "LAT": 35.936159181001415,
    "LNG": 127.17350209939177
  },
  {
    "NODE_ID": 27,
    "TYPE": "INTERMEDIATE",
    "LAT": 35.934395154833865,
    "LNG": 127.1731298756735
  },
  {
    "NODE_ID": 28,
    "TYPE": "STOP",
    "STOP_ID": 312101802,
    "LAT": 35.93394059,
    "LNG": 127.17291833
  },
  {
    "NODE_ID": 29,
    "TYPE": "INTERMEDIATE",
    "LAT": 35.93264051282643,
    "LNG": 127.1727562933195
  },
  {
    "NODE_ID": 30,
    "TYPE": "INTERMEDIATE",
    "LAT": 35.93087051133468,
    "LNG": 127.17243940072869
  },
  {
    "NODE_ID": 31,
    "TYPE": "INTERMEDIATE",
    "LAT": 35.929093203990064,
    "LNG": 127.17231033655654
  },
  {
    "NODE_ID": 32,
    "TYPE": "STOP",
    "STOP_ID": 305032549,
    "LAT": 35.9275584,
    "LNG": 127.1724836
  },
  {
    "NODE_ID": 33,
    "TYPE": "INTERMEDIATE",
    "LAT": 35.92742583382026,
    "LNG": 127.17250545807701
  },
  {
    "NODE_ID": 34,
    "TYPE": "INTERMEDIATE",
    "LAT": 35.925708305391446,
    "LNG": 127.17220669271516
  },
  {
    "NODE_ID": 35,
    "TYPE": "STOP",
    "STOP_ID": 305032385,
    "LAT": 35.9252687,
    "LNG": 127.1719388
  },
  {
    "NODE_ID": 36,
    "TYPE": "INTERMEDIATE",
    "LAT": 35.92428586319797,
    "LNG": 127.17093948240402
  },
  {
    "NODE_ID": 37,
    "TYPE": "INTERMEDIATE",
    "LAT": 35.923153226092595,
    "LNG": 127.16946664479458
  },
  {
    "NODE_ID": 38,
    "TYPE": "INTERMEDIATE",
    "LAT": 35.921643445890496,
    "LNG": 127.16843428635921
  },
  {
    "NODE_ID": 39,
    "TYPE": "INTERMEDIATE",
    "LAT": 35.92020960111037,
    "LNG": 127.16782783476198
  },
  {
    "NODE_ID": 40,
    "TYPE": "STOP",
    "STOP_ID": 312102029,
    "LAT": 35.92013308,
    "LNG": 127.1702271
  },
  {
    "NODE_ID": 41,
    "TYPE": "INTERMEDIATE",
    "LAT": 35.920173177957366,
    "LNG": 127.17003708614307
  },
  {
    "NODE_ID": 42,
    "TYPE": "INTERMEDIATE",
    "LAT": 35.9192120667681,
    "LNG": 127.1716960510644
  },
  {
    "NODE_ID": 43,
    "TYPE": "INTERMEDIATE",
    "LAT": 35.9179629794113,
    "LNG": 127.17329409577964
  },
  {
    "NODE_ID": 44,
    "TYPE": "INTERMEDIATE",
    "LAT": 35.91670073310439,
    "LNG": 127.17485996152833
  },
  {
    "NODE_ID": 45,
    "TYPE": "STOP",
    "STOP_ID": 312102027,
    "LAT": 35.91594461,
    "LNG": 127.17583291
  },
  {
    "NODE_ID": 46,
    "TYPE": "INTERMEDIATE",
    "LAT": 35.91546367530504,
    "LNG": 127.17645110371788
  },
  {
    "NODE_ID": 47,
    "TYPE": "INTERMEDIATE",
    "LAT": 35.91413703889933,
    "LNG": 127.17795075395766
  },
  {
    "NODE_ID": 48,
    "TYPE": "STOP",
    "STOP_ID": 312102025,
    "LAT": 35.91263963,
    "LNG": 127.17952891
  },
  {
    "NODE_ID": 49,
    "TYPE": "INTERMEDIATE",
    "LAT": 35.912854276078384,
    "LNG": 127.17947289735513
  },
  {
    "NODE_ID": 50,
    "TYPE": "INTERMEDIATE",
    "LAT": 35.91155664646391,
    "LNG": 127.18089878657135
  },
  {
    "NODE_ID": 51,
    "TYPE": "INTERMEDIATE",
    "LAT": 35.90993715082125,
    "LNG": 127.18155825945506
  },
  {
    "NODE_ID": 52,
    "TYPE": "STOP",
    "STOP_ID": 312101663,
    "LAT": 35.90909664,
    "LNG": 127.18212507
  },
  {
    "NODE_ID": 53,
    "TYPE": "INTERMEDIATE",
    "LAT": 35.908452967163235,
    "LNG": 127.18265893026913
  },
  {
    "NODE_ID": 54,
    "TYPE": "INTERMEDIATE",
    "LAT": 35.90687081806012,
    "LNG": 127.18340180432247
  },
  {
    "NODE_ID": 55,
    "TYPE": "STOP",
    "STOP_ID": 312032146,
    "LAT": 35.90529574,
    "LNG": 127.18441404
  },
  {
    "NODE_ID": 56,
    "TYPE": "INTERMEDIATE",
    "LAT": 35.90529842474465,
    "LNG": 127.18443065459608
  },
  {
    "NODE_ID": 57,
    "TYPE": "INTERMEDIATE",
    "LAT": 35.903667641262295,
    "LNG": 127.18531265085048
  },
  {
    "NODE_ID": 58,
    "TYPE": "STOP",
    "STOP_ID": 312101635,
    "LAT": 35.90349994,
    "LNG": 127.18501009
  },
  {
    "NODE_ID": 59,
    "TYPE": "INTERMEDIATE",
    "LAT": 35.90353278177609,
    "LNG": 127.18361983600893
  },
  {
    "NODE_ID": 60,
    "TYPE": "INTERMEDIATE",
    "LAT": 35.903637076960294,
    "LNG": 127.18142299044041
  },
  {
    "NODE_ID": 61,
    "TYPE": "INTERMEDIATE",
    "LAT": 35.90385740069678,
    "LNG": 127.1792398630556
  },
  {
    "NODE_ID": 62,
    "TYPE": "STOP",
    "STOP_ID": 312101652,
    "LAT": 35.90388552,
    "LNG": 127.17877556
  },
  {
    "NODE_ID": 63,
    "TYPE": "INTERMEDIATE",
    "LAT": 35.90396116949259,
    "LNG": 127.17701189622333
  },
  {
    "NODE_ID": 64,
    "TYPE": "INTERMEDIATE",
    "LAT": 35.904064422025726,
    "LNG": 127.17479501380316
  },
  {
    "NODE_ID": 65,
    "TYPE": "INTERMEDIATE",
    "LAT": 35.904250142888955,
    "LNG": 127.17260405623956
  },
  {
    "NODE_ID": 66,
    "TYPE": "STOP",
    "STOP_ID": 312101642,
    "LAT": 35.90451218,
    "LNG": 127.17092453
  },
  {
    "NODE_ID": 67,
    "TYPE": "INTERMEDIATE",
    "LAT": 35.90443171670679,
    "LNG": 127.17071834071099
  },
  {
    "NODE_ID": 68,
    "TYPE": "INTERMEDIATE",
    "LAT": 35.903901194314926,
    "LNG": 127.16865302083649
  },
  {
    "NODE_ID": 69,
    "TYPE": "STOP",
    "STOP_ID": 305032742,
    "LAT": 35.90378502,
    "LNG": 127.1673034
  },
  {
    "NODE_ID": 70,
    "TYPE": "INTERMEDIATE",
    "LAT": 35.90361517790643,
    "LNG": 127.16644949103748
  },
  {
    "NODE_ID": 71,
    "TYPE": "INTERMEDIATE",
    "LAT": 35.90348157602511,
    "LNG": 127.16424750886927
  },
  {
    "NODE_ID": 72,
    "TYPE": "INTERMEDIATE",
    "LAT": 35.90348575613041,
    "LNG": 127.16205225139068
  },
  {
    "NODE_ID": 73,
    "TYPE": "STOP",
    "STOP_ID": 312102030,
    "LAT": 35.90364372,
    "LNG": 127.16176944
  },
  {
    "NODE_ID": 74,
    "TYPE": "INTERMEDIATE",
    "LAT": 35.90395639994315,
    "LNG": 127.15993708455316
  },
  {
    "NODE_ID": 75,
    "TYPE": "STOP",
    "STOP_ID": 312102031,
    "LAT": 35.90422213,
    "LNG": 127.15812971
  },
  {
    "NODE_ID": 76,
    "TYPE": "INTERMEDIATE",
    "LAT": 35.90416660399473,
    "LNG": 127.15777838396308
  },
  {
    "NODE_ID": 77,
    "TYPE": "INTERMEDIATE",
    "LAT": 35.90323084211624,
    "LNG": 127.15676705125966
  },
  {
    "NODE_ID": 78,
    "TYPE": "INTERMEDIATE",
    "LAT": 35.90149070795433,
    "LNG": 127.15691957999233
  },
  {
    "NODE_ID": 79,
    "TYPE": "INTERMEDIATE",
    "LAT": 35.89983186204192,
    "LNG": 127.15661533334598
  },
  {
    "NODE_ID": 80,
    "TYPE": "STOP",
    "STOP_ID": 312101622,
    "LAT": 35.89917939,
    "LNG": 127.1560683
  },
  {
    "NODE_ID": 81,
    "TYPE": "INTERMEDIATE",
    "LAT": 35.89818811747409,
    "LNG": 127.1562310457286
  },
  {
    "NODE_ID": 82,
    "TYPE": "INTERMEDIATE",
    "LAT": 35.89647318742256,
    "LNG": 127.15662031958918
  },
  {
    "NODE_ID": 83,
    "TYPE": "INTERMEDIATE",
    "LAT": 35.89476848497038,
    "LNG": 127.15655477974292
  },
  {
    "NODE_ID": 84,
    "TYPE": "INTERMEDIATE",
    "LAT": 35.89308936718118,
    "LNG": 127.15597322917753
  },
  {
    "NODE_ID": 85,
    "TYPE": "INTERMEDIATE",
    "LAT": 35.89140555267939,
    "LNG": 127.1559139111684
  },
  {
    "NODE_ID": 86,
    "TYPE": "INTERMEDIATE",
    "LAT": 35.88963946147249,
    "LNG": 127.15619437185016
  },
  {
    "NODE_ID": 87,
    "TYPE": "STOP",
    "STOP_ID": 312101562,
    "LAT": 35.88886314,
    "LNG": 127.15617155
  },
  {
    "NODE_ID": 88,
    "TYPE": "INTERMEDIATE",
    "LAT": 35.8879185854343,
    "LNG": 127.15646638505424
  },
  {
    "NODE_ID": 89,
    "TYPE": "INTERMEDIATE",
    "LAT": 35.88620717443218,
    "LNG": 127.1564172745029
  },
  {
    "NODE_ID": 90,
    "TYPE": "STOP",
    "STOP_ID": 312101532,
    "LAT": 35.88433656,
    "LNG": 127.15601684
  },
  {
    "NODE_ID": 91,
    "TYPE": "INTERMEDIATE",
    "LAT": 35.884471600456436,
    "LNG": 127.15620538792112
  },
  {
    "NODE_ID": 92,
    "TYPE": "INTERMEDIATE",
    "LAT": 35.882726024804874,
    "LNG": 127.15600118142231
  },
  {
    "NODE_ID": 93,
    "TYPE": "STOP",
    "STOP_ID": 312101507,
    "LAT": 35.88140249,
    "LNG": 127.15566101
  },
  {
    "NODE_ID": 94,
    "TYPE": "INTERMEDIATE",
    "LAT": 35.88095352511689,
    "LNG": 127.15579130518644
  },
  {
    "NODE_ID": 95,
    "TYPE": "INTERMEDIATE",
    "LAT": 35.87926090131115,
    "LNG": 127.15602825773313
  },
  {
    "NODE_ID": 96,
    "TYPE": "INTERMEDIATE",
    "LAT": 35.87762265349639,
    "LNG": 127.15668644680535
  },
  {
    "NODE_ID": 97,
    "TYPE": "STOP",
    "STOP_ID": 312101461,
    "LAT": 35.87612216,
    "LNG": 127.15715693
  },
  {
    "NODE_ID": 98,
    "TYPE": "INTERMEDIATE",
    "LAT": 35.876022599309806,
    "LNG": 127.15717386888535
  },
  {
    "NODE_ID": 99,
    "TYPE": "INTERMEDIATE",
    "LAT": 35.87428505990153,
    "LNG": 127.15683856777795
  },
  {
    "NODE_ID": 100,
    "TYPE": "INTERMEDIATE",
    "LAT": 35.87268237156925,
    "LNG": 127.15712100983257
  },
  {
    "NODE_ID": 101,
    "TYPE": "STOP",
    "STOP_ID": 306101406,
    "LAT": 35.87126792,
    "LNG": 127.15812863
  },
  {
    "NODE_ID": 102,
    "TYPE": "INTERMEDIATE",
    "LAT": 35.871242730984186,
    "LNG": 127.15827551507304
  },
  {
    "NODE_ID": 103,
    "TYPE": "INTERMEDIATE",
    "LAT": 35.86973991716535,
    "LNG": 127.15933479366274
  },
  {
    "NODE_ID": 104,
    "TYPE": "STOP",
    "STOP_ID": 306101375,
    "LAT": 35.867997,
    "LNG": 127.160048
  },
  {
    "NODE_ID": 105,
    "TYPE": "INTERMEDIATE",
    "LAT": 35.86808740389017,
    "LNG": 127.16002458579027
  },
  {
    "NODE_ID": 106,
    "TYPE": "INTERMEDIATE",
    "LAT": 35.866424533927116,
    "LNG": 127.16032401878708
  },
  {
    "NODE_ID": 107,
    "TYPE": "STOP",
    "STOP_ID": 306101335,
    "LAT": 35.86564054,
    "LNG": 127.16027593
  },
  {
    "NODE_ID": 108,
    "TYPE": "INTERMEDIATE",
    "LAT": 35.86464437943311,
    "LNG": 127.16027816483744
  },
  {
    "NODE_ID": 109,
    "TYPE": "INTERMEDIATE",
    "LAT": 35.86294853622618,
    "LNG": 127.15993762851096
  },
  {
    "NODE_ID": 110,
    "TYPE": "STOP",
    "STOP_ID": 306101293,
    "LAT": 35.86262591,
    "LNG": 127.15972862
  },
  {
    "NODE_ID": 111,
    "TYPE": "INTERMEDIATE",
    "LAT": 35.86126683082908,
    "LNG": 127.15932476799496
  },
  {
    "NODE_ID": 112,
    "TYPE": "INTERMEDIATE",
    "LAT": 35.8595850728844,
    "LNG": 127.15871309889026
  },
  {
    "NODE_ID": 113,
    "TYPE": "STOP",
    "STOP_ID": 306101252,
    "LAT": 35.858764,
    "LNG": 127.158203
  },
  {
    "NODE_ID": 114,
    "TYPE": "INTERMEDIATE",
    "LAT": 35.85804627398985,
    "LNG": 127.15776439564043
  },
  {
    "NODE_ID": 115,
    "TYPE": "INTERMEDIATE",
    "LAT": 35.8565725095553,
    "LNG": 127.15677035450327
  },
  {
    "NODE_ID": 116,
    "TYPE": "INTERMEDIATE",
    "LAT": 35.854935579219834,
    "LNG": 127.1575117710416
  },
  {
    "NODE_ID": 117,
    "TYPE": "STOP",
    "STOP_ID": 306101193,
    "LAT": 35.85455441,
    "LNG": 127.15760015
  },
  {
    "NODE_ID": 118,
    "TYPE": "INTERMEDIATE",
    "LAT": 35.853354455059005,
    "LNG": 127.15830998883342
  },
  {
    "NODE_ID": 119,
    "TYPE": "INTERMEDIATE",
    "LAT": 35.85170555760595,
    "LNG": 127.15913933649118
  },
  {
    "NODE_ID": 120,
    "TYPE": "INTERMEDIATE",
    "LAT": 35.850080845433254,
    "LNG": 127.15995308079083
  },
  {
    "NODE_ID": 121,
    "TYPE": "INTERMEDIATE",
    "LAT": 35.84904244564409,
    "LNG": 127.1595094171054
  },
  {
    "NODE_ID": 122,
    "TYPE": "STOP",
    "STOP_ID": 306101110,
    "LAT": 35.8488499,
    "LNG": 127.1588352
  },
  {
    "NODE_ID": 123,
    "TYPE": "INTERMEDIATE",
    "LAT": 35.84834777903075,
    "LNG": 127.1575108871611
  },
  {
    "NODE_ID": 124,
    "TYPE": "INTERMEDIATE",
    "LAT": 35.847655919233596,
    "LNG": 127.15551080960884
  },
  {
    "NODE_ID": 125,
    "TYPE": "STOP",
    "STOP_ID": 306101092,
    "LAT": 35.847489,
    "LNG": 127.155193
  },
  {
    "NODE_ID": 126,
    "TYPE": "INTERMEDIATE",
    "LAT": 35.84697734326183,
    "LNG": 127.15351612643904
  },
  {
    "NODE_ID": 127,
    "TYPE": "INTERMEDIATE",
    "LAT": 35.845810614404826,
    "LNG": 127.15286709250353
  },
  {
    "NODE_ID": 128,
    "TYPE": "STOP",
    "STOP_ID": 306101080,
    "LAT": 35.84548171,
    "LNG": 127.15287844
  },
  {
    "NODE_ID": 129,
    "TYPE": "INTERMEDIATE",
    "LAT": 35.844117029643016,
    "LNG": 127.15354550290371
  },
  {
    "NODE_ID": 130,
    "TYPE": "INTERMEDIATE",
    "LAT": 35.84312504925169,
    "LNG": 127.15234648642422
  },
  {
    "NODE_ID": 131,
    "TYPE": "STOP",
    "STOP_ID": 306101048,
    "LAT": 35.8426526,
    "LNG": 127.15200998
  },
  {
    "NODE_ID": 132,
    "TYPE": "INTERMEDIATE",
    "LAT": 35.84150185034254,
    "LNG": 127.15162240267529
  },
  {
    "NODE_ID": 133,
    "TYPE": "INTERMEDIATE",
    "LAT": 35.839773277232474,
    "LNG": 127.15135308742788
  },
  {
    "NODE_ID": 134,
    "TYPE": "STOP",
    "STOP_ID": 306100992,
    "LAT": 35.83782996,
    "LNG": 127.15075133
  },
  {
    "NODE_ID": 135,
    "TYPE": "INTERMEDIATE",
    "LAT": 35.838009987810366,
    "LNG": 127.15086220377445
  },
  {
    "NODE_ID": 136,
    "TYPE": "INTERMEDIATE",
    "LAT": 35.836306651211096,
    "LNG": 127.15031235510769
  },
  {
    "NODE_ID": 137,
    "TYPE": "INTERMEDIATE",
    "LAT": 35.835429671346375,
    "LNG": 127.14871610476109
  },
  {
    "NODE_ID": 138,
    "TYPE": "STOP",
    "STOP_ID": 306100943,
    "LAT": 35.83506423,
    "LNG": 127.14759274
  },
  {
    "NODE_ID": 139,
    "TYPE": "INTERMEDIATE",
    "LAT": 35.834486462431876,
    "LNG": 127.14685302825374
  },
  {
    "NODE_ID": 140,
    "TYPE": "INTERMEDIATE",
    "LAT": 35.83323580337766,
    "LNG": 127.14532179406557
  },
  {
    "NODE_ID": 141,
    "TYPE": "STOP",
    "STOP_ID": 306100898,
    "LAT": 35.83301705,
    "LNG": 127.14490334
  },
  {
    "NODE_ID": 142,
    "TYPE": "INTERMEDIATE",
    "LAT": 35.83195370188603,
    "LNG": 127.14381367498451
  },
  {
    "NODE_ID": 143,
    "TYPE": "INTERMEDIATE",
    "LAT": 35.83069596452288,
    "LNG": 127.14232231845617
  },
  {
    "NODE_ID": 144,
    "TYPE": "INTERMEDIATE",
    "LAT": 35.82942245126084,
    "LNG": 127.14252038793674
  },
  {
    "NODE_ID": 145,
    "TYPE": "STOP",
    "STOP_ID": 306100827,
    "LAT": 35.82894399,
    "LNG": 127.14283256
  },
  {
    "NODE_ID": 146,
    "TYPE": "INTERMEDIATE",
    "LAT": 35.828155367732386,
    "LNG": 127.14407916354313
  },
  {
    "NODE_ID": 147,
    "TYPE": "INTERMEDIATE",
    "LAT": 35.82692503312994,
    "LNG": 127.14555612197503
  },
  {
    "NODE_ID": 148,
    "TYPE": "STOP",
    "STOP_ID": 306100781,
    "LAT": 35.82578923,
    "LNG": 127.1465455
  },
  {
    "NODE_ID": 149,
    "TYPE": "INTERMEDIATE",
    "LAT": 35.82560753962806,
    "LNG": 127.14703353373537
  },
  {
    "NODE_ID": 150,
    "TYPE": "INTERMEDIATE",
    "LAT": 35.82433885231595,
    "LNG": 127.14845999302355
  },
  {
    "NODE_ID": 151,
    "TYPE": "STOP",
    "STOP_ID": 306100731,
    "LAT": 35.82307474,
    "LNG": 127.14967928
  },
  {
    "NODE_ID": 152,
    "TYPE": "INTERMEDIATE",
    "LAT": 35.82304674715774,
    "LNG": 127.14995487129852
  },
  {
    "NODE_ID": 153,
    "TYPE": "INTERMEDIATE",
    "LAT": 35.82176863244189,
    "LNG": 127.15141944434174
  },
  {
    "NODE_ID": 154,
    "TYPE": "STOP",
    "STOP_ID": 305100703,
    "LAT": 35.82096,
    "LNG": 127.15228
  },
  {
    "NODE_ID": 155,
    "TYPE": "INTERMEDIATE",
    "LAT": 35.82060373342599,
    "LNG": 127.15270219395777
  },
  {
    "NODE_ID": 156,
    "TYPE": "STOP",
    "STOP_ID": 305100681,
    "LAT": 35.81983521,
    "LNG": 127.15058311
  },
  {
    "NODE_ID": 157,
    "TYPE": "INTERMEDIATE",
    "LAT": 35.819802626422145,
    "LNG": 127.15085843110992
  },
  {
    "NODE_ID": 158,
    "TYPE": "INTERMEDIATE",
    "LAT": 35.81926682512066,
    "LNG": 127.14884726872755
  },
  {
    "NODE_ID": 159,
    "TYPE": "INTERMEDIATE",
    "LAT": 35.818723882516814,
    "LNG": 127.1468515126173
  },
  {
    "NODE_ID": 160,
    "TYPE": "STOP",
    "STOP_ID": 305100645,
    "LAT": 35.817028,
    "LNG": 127.147313
  },
  {
    "NODE_ID": 161,
    "TYPE": "INTERMEDIATE",
    "LAT": 35.8170812001683,
    "LNG": 127.14735924622084
  },
  {
    "NODE_ID": 162,
    "TYPE": "STOP",
    "STOP_ID": 305100628,
    "LAT": 35.81594824,
    "LNG": 127.14699101
  },
  {
    "NODE_ID": 163,
    "TYPE": "INTERMEDIATE",
    "LAT": 35.81589948991321,
    "LNG": 127.1471504123924
  },
  {
    "NODE_ID": 164,
    "TYPE": "INTERMEDIATE",
    "LAT": 35.815585382283054,
    "LNG": 127.1451225108091
  },
  {
    "NODE_ID": 165,
    "TYPE": "INTERMEDIATE",
    "LAT": 35.81521963484199,
    "LNG": 127.14316077047874
  },
  {
    "NODE_ID": 166,
    "TYPE": "STOP",
    "STOP_ID": 305100611,
    "LAT": 35.81515762,
    "LNG": 127.14274571
  },
  {
    "NODE_ID": 167,
    "TYPE": "INTERMEDIATE",
    "LAT": 35.814388396977364,
    "LNG": 127.1412207168119
  },
  {
    "NODE_ID": 168,
    "TYPE": "INTERMEDIATE",
    "LAT": 35.8132705737179,
    "LNG": 127.13967844574815
  },
  {
    "NODE_ID": 169,
    "TYPE": "STOP",
    "STOP_ID": 305100568,
    "LAT": 35.81225757,
    "LNG": 127.13903665
  },
  {
    "NODE_ID": 170,
    "TYPE": "INTERMEDIATE",
    "LAT": 35.81170461119681,
    "LNG": 127.1388547292058
  },
  {
    "NODE_ID": 171,
    "TYPE": "INTERMEDIATE",
    "LAT": 35.81014102333922,
    "LNG": 127.13795429729261
  },
  {
    "NODE_ID": 172,
    "TYPE": "INTERMEDIATE",
    "LAT": 35.80906351112657,
    "LNG": 127.13635344744085
  },
  {
    "NODE_ID": 173,
    "TYPE": "STOP",
    "STOP_ID": 305100538,
    "LAT": 35.808837,
    "LNG": 127.135618
  },
  {
    "NODE_ID": 174,
    "TYPE": "INTERMEDIATE",
    "LAT": 35.808417776714464,
    "LNG": 127.13430786414796
  },
  {
    "NODE_ID": 175,
    "TYPE": "INTERMEDIATE",
    "LAT": 35.80771332918073,
    "LNG": 127.13232969229675
  },
  {
    "NODE_ID": 176,
    "TYPE": "STOP",
    "STOP_ID": 305100525,
    "LAT": 35.807223,
    "LNG": 127.130662
  },
  {
    "NODE_ID": 177,
    "TYPE": "INTERMEDIATE",
    "LAT": 35.80705047582409,
    "LNG": 127.13027988456898
  },
  {
    "NODE_ID": 178,
    "TYPE": "INTERMEDIATE",
    "LAT": 35.80647518589036,
    "LNG": 127.12829239469144
  },
  {
    "NODE_ID": 179,
    "TYPE": "INTERMEDIATE",
    "LAT": 35.8059906048041,
    "LNG": 127.12620065129822
  },
  {
    "NODE_ID": 180,
    "TYPE": "STOP",
    "STOP_ID": 305100509,
    "LAT": 35.805948,
    "LNG": 127.125855
  },
  {
    "NODE_ID": 181,
    "TYPE": "INTERMEDIATE",
    "LAT": 35.80590046846348,
    "LNG": 127.12405082843371
  },
  {
    "NODE_ID": 182,
    "TYPE": "INTERMEDIATE",
    "LAT": 35.80614335876908,
    "LNG": 127.12190029309814
  },
  {
    "NODE_ID": 183,
    "TYPE": "STOP",
    "STOP_ID": 305100514,
    "LAT": 35.806287,
    "LNG": 127.120957
  },
  {
    "NODE_ID": 184,
    "TYPE": "INTERMEDIATE",
    "LAT": 35.80638148152192,
    "LNG": 127.11972860660906
  },
  {
    "NODE_ID": 185,
    "TYPE": "STOP",
    "STOP_ID": 305100520,
    "LAT": 35.80670585,
    "LNG": 127.1175812
  },
  {
    "NODE_ID": 186,
    "TYPE": "INTERMEDIATE",
    "LAT": 35.80664629928214,
    "LNG": 127.11754663847047
  },
  {
    "NODE_ID": 187,
    "TYPE": "INTERMEDIATE",
    "LAT": 35.80784945501835,
    "LNG": 127.11630745477964
  },
  {
    "NODE_ID": 188,
    "TYPE": "INTERMEDIATE",
    "LAT": 35.809499062267435,
    "LNG": 127.11548428009635
  },
  {
    "NODE_ID": 189,
    "TYPE": "STOP",
    "STOP_ID": 305100553,
    "LAT": 35.81107333,
    "LNG": 127.11475989
  },
  {
    "NODE_ID": 190,
    "TYPE": "INTERMEDIATE",
    "LAT": 35.811132729704276,
    "LNG": 127.11466868354343
  },
  {
    "NODE_ID": 191,
    "TYPE": "STOP",
    "STOP_ID": 305100576,
    "LAT": 35.81288005,
    "LNG": 127.11388786
  },
  {
    "NODE_ID": 192,
    "TYPE": "INTERMEDIATE",
    "LAT": 35.81279471216558,
    "LNG": 127.11385025370502
  },
  {
    "NODE_ID": 193,
    "TYPE": "INTERMEDIATE",
    "LAT": 35.81369882038032,
    "LNG": 127.11235159851451
  },
  {
    "NODE_ID": 194,
    "TYPE": "INTERMEDIATE",
    "LAT": 35.813702959963685,
    "LNG": 127.1102005444874
  },
  {
    "NODE_ID": 195,
    "TYPE": "STOP",
    "STOP_ID": 305100592,
    "LAT": 35.81381547,
    "LNG": 127.1080203
  },
  {
    "NODE_ID": 196,
    "TYPE": "INTERMEDIATE",
    "LAT": 35.81369807851919,
    "LNG": 127.10797144534932
  },
  {
    "NODE_ID": 197,
    "TYPE": "INTERMEDIATE",
    "LAT": 35.813694309434084,
    "LNG": 127.10579779593996
  },
  {
    "NODE_ID": 198,
    "TYPE": "STOP",
    "STOP_ID": 305102001,
    "LAT": 35.813757,
    "LNG": 127.103754
  },
  {
    "NODE_ID": 199,
    "TYPE": "INTERMEDIATE",
    "LAT": 35.81370052852234,
    "LNG": 127.1035687018668
  },
  {
    "NODE_ID": 200,
    "TYPE": "INTERMEDIATE",
    "LAT": 35.81370647787171,
    "LNG": 127.10139505794304
  },
  {
    "NODE_ID": 201,
    "TYPE": "INTERMEDIATE",
    "LAT": 35.8137135154196,
    "LNG": 127.09917705726596
  },
  {
    "NODE_ID": 202,
    "TYPE": "STOP",
    "STOP_ID": 305100591,
    "LAT": 35.81379234,
    "LNG": 127.09796491
  },
  {
    "NODE_ID": 203,
    "TYPE": "INTERMEDIATE",
    "LAT": 35.81372058815523,
    "LNG": 127.09694796658552
  },
  {
    "NODE_ID": 204,
    "TYPE": "INTERMEDIATE",
    "LAT": 35.813727625703116,
    "LNG": 127.09472996590844
  },
  {
    "NODE_ID": 205,
    "TYPE": "INTERMEDIATE",
    "LAT": 35.81533660396956,
    "LNG": 127.09473193171615
  },
  {
    "NODE_ID": 206,
    "TYPE": "STOP",
    "STOP_ID": 305100630,
    "LAT": 35.816115,
    "LNG": 127.094854
  },
  {
    "NODE_ID": 207,
    "TYPE": "INTERMEDIATE",
    "LAT": 35.81714406313583,
    "LNG": 127.09470071404952
  },
  {
    "NODE_ID": 208,
    "TYPE": "INTERMEDIATE",
    "LAT": 35.818131966350215,
    "LNG": 127.09345944807762
  },
  {
    "NODE_ID": 209,
    "TYPE": "STOP",
    "STOP_ID": 305100651,
    "LAT": 35.81862,
    "LNG": 127.092247
  },
  {
    "NODE_ID": 210,
    "TYPE": "INTERMEDIATE",
    "LAT": 35.81890583758961,
    "LNG": 127.09152616977656
  },
  {
    "NODE_ID": 211,
    "TYPE": "INTERMEDIATE",
    "LAT": 35.81985794749209,
    "LNG": 127.08971017568237
  },
  {
    "NODE_ID": 212,
    "TYPE": "INTERMEDIATE",
    "LAT": 35.82080800274996,
    "LNG": 127.08787953025025
  }
]