{
  "resultList": [
    {
      "NODE_ID": 0,
      "LAT": 35.8242298,
      "LNG": 127.1795887,
      "TYPE": "STOP",
      "STOP_ID": 305032318,
      "matched": null
    },
    {
      "NODE_ID": 1,
      "LAT": 35.82453163847376,
      "LNG": 127.1785542078415,
      "TYPE": "INTERMEDIATE",
      "matched": null
    },
    {
      "NODE_ID": 2,
      "LAT": 35.826180278875675,
      "LNG": 127.17766729710816,
      "TYPE": "INTERMEDIATE",
      "matched": null
    },
    {
      "NODE_ID": 3,
      "LAT": 35.82782891927759,
      "LNG": 127.17678038637482,
      "TYPE": "INTERMEDIATE",
      "matched": {
        "id": 3058002500,
        "sub": 0,
        "distance": 9.26781530432338
      }
    },
    {
      "NODE_ID": 4,
      "LAT": 35.82946334994409,
      "LNG": 127.17589161377894,
      "TYPE": "INTERMEDIATE",
      "matched": {
        "id": 3058002500,
        "sub": 0,
        "distance": 9.26781530432338
      }
    },
    {
      "NODE_ID": 5,
      "LAT": 35.82881735669137,
      "LNG": 127.17387203376765,
      "TYPE": "INTERMEDIATE",
      "matched": {
        "id": 3058002500,
        "sub": 0,
        "distance": 9.26781530432338
      }
    },
    {
      "NODE_ID": 6,
      "LAT": 35.828744,
      "LNG": 127.173486,
      "TYPE": "STOP",
      "STOP_ID": 306100825,
      "matched": {
        "id": 3058002500,
        "sub": 0,
        "distance": 9.26781530432338
      }
    },
    {
      "NODE_ID": 7,
      "LAT": 35.82811440291796,
      "LNG": 127.1718904815142,
      "TYPE": "INTERMEDIATE",
      "matched": {
        "id": 3058002500,
        "sub": 0,
        "distance": 9.26781530432338
      }
    },
    {
      "NODE_ID": 8,
      "LAT": 35.827822,
      "LNG": 127.170761,
      "TYPE": "STOP",
      "STOP_ID": 306100815,
      "matched": {
        "id": 3058002500,
        "sub": 0,
        "distance": 9.26781530432338
      }
    },
    {
      "NODE_ID": 9,
      "LAT": 35.8274013012906,
      "LNG": 127.16991464042901,
      "TYPE": "INTERMEDIATE",
      "matched": {
        "id": 3058002500,
        "sub": 0,
        "distance": 9.26781530432338
      }
    },
    {
      "NODE_ID": 10,
      "LAT": 35.82678,
      "LNG": 127.167751,
      "TYPE": "STOP",
      "STOP_ID": 306100801,
      "matched": {
        "id": 3058002500,
        "sub": 0,
        "distance": 9.26781530432338
      }
    },
    {
      "NODE_ID": 11,
      "LAT": 35.82671483693501,
      "LNG": 127.16794909803696,
      "TYPE": "INTERMEDIATE",
      "matched": {
        "id": 3058002500,
        "sub": 0,
        "distance": 9.26781530432338
      }
    },
    {
      "NODE_ID": 12,
      "LAT": 35.826152512557734,
      "LNG": 127.16627407096968,
      "TYPE": "INTERMEDIATE",
      "matched": {
        "id": 3058002500,
        "sub": 0,
        "distance": 9.26781530432338
      }
    },
    {
      "NODE_ID": 13,
      "LAT": 35.827071,
      "LNG": 127.165809,
      "TYPE": "STOP",
      "STOP_ID": 306100806,
      "matched": {
        "id": 3058002500,
        "sub": 0,
        "distance": 9.26781530432338
      }
    },
    {
      "NODE_ID": 14,
      "LAT": 35.82775986609391,
      "LNG": 127.16529607453839,
      "TYPE": "INTERMEDIATE",
      "matched": {
        "id": 3058002500,
        "sub": 0,
        "distance": 9.26781530432338
      }
    },
    {
      "NODE_ID": 15,
      "LAT": 35.82924961,
      "LNG": 127.16430729,
      "TYPE": "STOP",
      "STOP_ID": 306100836,
      "matched": {
        "id": 3058002500,
        "sub": 0,
        "distance": 9.26781530432338
      }
    },
    {
      "NODE_ID": 16,
      "LAT": 35.82921265439323,
      "LNG": 127.16421192361113,
      "TYPE": "INTERMEDIATE",
      "matched": {
        "id": 3058002500,
        "sub": 0,
        "distance": 9.26781530432338
      }
    },
    {
      "NODE_ID": 17,
      "LAT": 35.8309241620288,
      "LNG": 127.1635297910749,
      "TYPE": "INTERMEDIATE",
      "matched": {
        "id": 3058002500,
        "sub": 0,
        "distance": 9.26781530432338
      }
    },
    {
      "NODE_ID": 18,
      "LAT": 35.832869,
      "LNG": 127.162896,
      "TYPE": "STOP",
      "STOP_ID": 306100897,
      "matched": {
        "id": 3058002500,
        "sub": 0,
        "distance": 9.26781530432338
      }
    },
    {
      "NODE_ID": 19,
      "LAT": 35.832610212659084,
      "LNG": 127.16293530272256,
      "TYPE": "INTERMEDIATE",
      "matched": {
        "id": 3058002500,
        "sub": 0,
        "distance": 9.26781530432338
      }
    },
    {
      "NODE_ID": 20,
      "LAT": 35.834173215750305,
      "LNG": 127.16223053085136,
      "TYPE": "INTERMEDIATE",
      "matched": {
        "id": 3058015400,
        "sub": 3,
        "distance": 12.196537240497197
      }
    },
    {
      "NODE_ID": 21,
      "LAT": 35.8337595453835,
      "LNG": 127.16014364422492,
      "TYPE": "INTERMEDIATE",
      "matched": {
        "id": 3058015300,
        "sub": 1,
        "distance": 28.90794551241947
      }
    },
    {
      "NODE_ID": 22,
      "LAT": 35.833611969073104,
      "LNG": 127.15794368567796,
      "TYPE": "INTERMEDIATE",
      "matched": {
        "id": 3058016700,
        "sub": 1,
        "distance": 8.008444735473224
      }
    },
    {
      "NODE_ID": 23,
      "LAT": 35.83217988,
      "LNG": 127.15824254,
      "TYPE": "STOP",
      "STOP_ID": 306100881,
      "matched": {
        "id": 3058016700,
        "sub": 1,
        "distance": 8.008444735473224
      }
    },
    {
      "NODE_ID": 24,
      "LAT": 35.83194526741165,
      "LNG": 127.15837863754872,
      "TYPE": "INTERMEDIATE",
      "matched": {
        "id": 3058016700,
        "sub": 1,
        "distance": 8.008444735473224
      }
    },
    {
      "NODE_ID": 25,
      "LAT": 35.83024555407147,
      "LNG": 127.15906105347362,
      "TYPE": "INTERMEDIATE",
      "matched": {
        "id": 3058016700,
        "sub": 1,
        "distance": 8.008444735473224
      }
    },
    {
      "NODE_ID": 26,
      "LAT": 35.830003,
      "LNG": 127.157344,
      "TYPE": "STOP",
      "STOP_ID": 306100846,
      "matched": {
        "id": 3058016700,
        "sub": 1,
        "distance": 8.008444735473224
      }
    },
    {
      "NODE_ID": 27,
      "LAT": 35.82998707187224,
      "LNG": 127.15719937982641,
      "TYPE": "INTERMEDIATE",
      "matched": {
        "id": 3058016700,
        "sub": 1,
        "distance": 8.008444735473224
      }
    },
    {
      "NODE_ID": 28,
      "LAT": 35.82969861051258,
      "LNG": 127.15505460332318,
      "TYPE": "INTERMEDIATE",
      "matched": {
        "id": 3058016900,
        "sub": 9,
        "distance": 76.46439011133357
      }
    },
    {
      "NODE_ID": 29,
      "LAT": 35.82899531,
      "LNG": 127.15396039,
      "TYPE": "STOP",
      "STOP_ID": 305100829,
      "matched": {
        "id": 3058017000,
        "sub": 6,
        "distance": 48.1712155081384
      }
    },
    {
      "NODE_ID": 30,
      "LAT": 35.82877929485739,
      "LNG": 127.15406411650923,
      "TYPE": "INTERMEDIATE",
      "matched": {
        "id": 3058017000,
        "sub": 6,
        "distance": 72.20082552378094
      }
    },
    {
      "NODE_ID": 31,
      "LAT": 35.827389,
      "LNG": 127.154002,
      "TYPE": "STOP",
      "STOP_ID": 305100804,
      "matched": {
        "id": 3058016900,
        "sub": 4,
        "distance": 14.880958272604934
      }
    },
    {
      "NODE_ID": 32,
      "LAT": 35.82708224458417,
      "LNG": 127.15375297619448,
      "TYPE": "INTERMEDIATE",
      "matched": {
        "id": 3058017000,
        "sub": 3,
        "distance": 25.064449252606362
      }
    },
    {
      "NODE_ID": 33,
      "LAT": 35.82552779305627,
      "LNG": 127.15283644061054,
      "TYPE": "INTERMEDIATE",
      "matched": {
        "id": 3058017000,
        "sub": 1,
        "distance": 15.456497546601561
      }
    },
    {
      "NODE_ID": 34,
      "LAT": 35.824177,
      "LNG": 127.152672,
      "TYPE": "STOP",
      "STOP_ID": 305100748,
      "matched": {
        "id": 3058017000,
        "sub": 1,
        "distance": 15.456497546601561
      }
    },
    {
      "NODE_ID": 35,
      "LAT": 35.823747732994946,
      "LNG": 127.15251842272824,
      "TYPE": "INTERMEDIATE",
      "matched": {
        "id": 3058016900,
        "sub": 1,
        "distance": 62.5902280430648
      }
    },
    {
      "NODE_ID": 36,
      "LAT": 35.82206370526785,
      "LNG": 127.15265561363391,
      "TYPE": "INTERMEDIATE",
      "matched": {
        "id": 3058019400,
        "sub": 2,
        "distance": 87.46741695444186
      }
    },
    {
      "NODE_ID": 37,
      "LAT": 35.82046539903462,
      "LNG": 127.15250431192207,
      "TYPE": "INTERMEDIATE",
      "matched": {
        "id": 3058020300,
        "sub": 3,
        "distance": 21.827540227103313
      }
    },
    {
      "NODE_ID": 38,
      "LAT": 35.81983521,
      "LNG": 127.15058311,
      "TYPE": "STOP",
      "STOP_ID": 305100681,
      "matched": {
        "id": 3058020300,
        "sub": 2,
        "distance": 75.33086792539589
      }
    },
    {
      "NODE_ID": 39,
      "LAT": 35.81973292171627,
      "LNG": 127.15062363969828,
      "TYPE": "INTERMEDIATE",
      "matched": {
        "id": 3058020400,
        "sub": 2,
        "distance": 75.20226708586361
      }
    },
    {
      "NODE_ID": 40,
      "LAT": 35.81920797721892,
      "LNG": 127.14859645073206,
      "TYPE": "INTERMEDIATE",
      "matched": {
        "id": 3058020300,
        "sub": 1,
        "distance": 13.405526486892537
      }
    },
    {
      "NODE_ID": 41,
      "LAT": 35.81878592350109,
      "LNG": 127.14689470225447,
      "TYPE": "INTERMEDIATE",
      "matched": {
        "id": 3058005500,
        "sub": 5,
        "distance": 6.905710399912728
      }
    },
    {
      "NODE_ID": 42,
      "LAT": 35.820099,
      "LNG": 127.146497,
      "TYPE": "STOP",
      "STOP_ID": 305100683,
      "matched": {
        "id": 3058005500,
        "sub": 5,
        "distance": 6.905710399912728
      }
    },
    {
      "NODE_ID": 43,
      "LAT": 35.82049388083985,
      "LNG": 127.14623548412041,
      "TYPE": "INTERMEDIATE",
      "matched": {
        "id": 3058005500,
        "sub": 5,
        "distance": 6.905710399912728
      }
    },
    {
      "NODE_ID": 44,
      "LAT": 35.82211222111215,
      "LNG": 127.14559569535953,
      "TYPE": "INTERMEDIATE",
      "matched": {
        "id": 3058005300,
        "sub": 1,
        "distance": 11.59070105164012
      }
    },
    {
      "NODE_ID": 45,
      "LAT": 35.82371351936705,
      "LNG": 127.1449286127159,
      "TYPE": "INTERMEDIATE",
      "matched": {
        "id": 3058005300,
        "sub": 1,
        "distance": 11.59070105164012
      }
    },
    {
      "NODE_ID": 46,
      "LAT": 35.824475,
      "LNG": 127.144695,
      "TYPE": "STOP",
      "STOP_ID": 306100752,
      "matched": {
        "id": 3058005300,
        "sub": 1,
        "distance": 11.59070105164012
      }
    },
    {
      "NODE_ID": 47,
      "LAT": 35.82538136190391,
      "LNG": 127.14422629621237,
      "TYPE": "INTERMEDIATE",
      "matched": {
        "id": 3058005300,
        "sub": 1,
        "distance": 11.59070105164012
      }
    },
    {
      "NODE_ID": 48,
      "LAT": 35.82698337626153,
      "LNG": 127.14352782132345,
      "TYPE": "INTERMEDIATE",
      "matched": {
        "id": 3058005300,
        "sub": 2,
        "distance": 13.803540097745714
      }
    },
    {
      "NODE_ID": 49,
      "LAT": 35.82824080870711,
      "LNG": 127.14206473359185,
      "TYPE": "INTERMEDIATE",
      "matched": {
        "id": 3058019200,
        "sub": 0,
        "distance": 4.3403160188720085
      }
    },
    {
      "NODE_ID": 50,
      "LAT": 35.829235519595876,
      "LNG": 127.14056809905154,
      "TYPE": "INTERMEDIATE",
      "matched": {
        "id": 3058019200,
        "sub": 0,
        "distance": 4.3403160188720085
      }
    },
    {
      "NODE_ID": 51,
      "LAT": 35.83055688784282,
      "LNG": 127.13931345150914,
      "TYPE": "INTERMEDIATE",
      "matched": {
        "id": 3058005100,
        "sub": 2,
        "distance": 15.867509022883036
      }
    },
    {
      "NODE_ID": 52,
      "LAT": 35.83141844,
      "LNG": 127.13871665,
      "TYPE": "STOP",
      "STOP_ID": 306100861,
      "matched": {
        "id": 3058005100,
        "sub": 2,
        "distance": 94.04043809808196
      }
    },
    {
      "NODE_ID": 53,
      "LAT": 35.83203235104454,
      "LNG": 127.13806423003538,
      "TYPE": "INTERMEDIATE",
      "matched": {
        "id": 3058004400,
        "sub": 1,
        "distance": 22.97222956337987
      }
    },
    {
      "NODE_ID": 54,
      "LAT": 35.83351237027854,
      "LNG": 127.13686331196068,
      "TYPE": "INTERMEDIATE",
      "matched": {
        "id": 3058004400,
        "sub": 1,
        "distance": 22.97222956337987
      }
    },
    {
      "NODE_ID": 55,
      "LAT": 35.83492161379492,
      "LNG": 127.13574576662243,
      "TYPE": "INTERMEDIATE",
      "matched": {
        "id": 3058004100,
        "sub": 0,
        "distance": 13.070360461753612
      }
    },
    {
      "NODE_ID": 56,
      "LAT": 35.834308613804204,
      "LNG": 127.13376800350954,
      "TYPE": "INTERMEDIATE",
      "matched": {
        "id": 3058004100,
        "sub": 0,
        "distance": 13.070360461753612
      }
    },
    {
      "NODE_ID": 57,
      "LAT": 35.83437333,
      "LNG": 127.13328615,
      "TYPE": "STOP",
      "STOP_ID": 306100927,
      "matched": {
        "id": 3058004100,
        "sub": 0,
        "distance": 13.070360461753612
      }
    },
    {
      "NODE_ID": 58,
      "LAT": 35.83409205263565,
      "LNG": 127.1315658373552,
      "TYPE": "INTERMEDIATE",
      "matched": {
        "id": 3058018100,
        "sub": 0,
        "distance": 31.7750602187398
      }
    },
    {
      "NODE_ID": 59,
      "LAT": 35.83418203,
      "LNG": 127.1303235,
      "TYPE": "STOP",
      "STOP_ID": 306100925,
      "matched": {
        "id": 3058018100,
        "sub": 1,
        "distance": 45.44307828646141
      }
    },
    {
      "NODE_ID": 60,
      "LAT": 35.834266628990235,
      "LNG": 127.12942064194631,
      "TYPE": "INTERMEDIATE",
      "matched": {
        "id": 3058032800,
        "sub": 3,
        "distance": 27.495082264360438
      }
    },
    {
      "NODE_ID": 61,
      "LAT": 35.834554118030574,
      "LNG": 127.12727555940475,
      "TYPE": "INTERMEDIATE",
      "matched": {
        "id": 3058032800,
        "sub": 3,
        "distance": 27.495082264360438
      }
    },
    {
      "NODE_ID": 62,
      "LAT": 35.83487104,
      "LNG": 127.12591932,
      "TYPE": "STOP",
      "STOP_ID": 306100946,
      "matched": {
        "id": 3058018500,
        "sub": 1,
        "distance": 1.2728689474791344
      }
    },
    {
      "NODE_ID": 63,
      "LAT": 35.83495948949723,
      "LNG": 127.12512822732715,
      "TYPE": "INTERMEDIATE",
      "matched": {
        "id": 3058018600,
        "sub": 2,
        "distance": 25.020219751715622
      }
    },
    {
      "NODE_ID": 64,
      "LAT": 35.83506339400537,
      "LNG": 127.12341290032458,
      "TYPE": "INTERMEDIATE",
      "matched": {
        "id": 3058018600,
        "sub": 3,
        "distance": 40.92482774762064
      }
    },
    {
      "NODE_ID": 65,
      "LAT": 35.833457401574755,
      "LNG": 127.12279196623578,
      "TYPE": "INTERMEDIATE",
      "matched": {
        "id": 3058019000,
        "sub": 0,
        "distance": 35.290920310367014
      }
    },
    {
      "NODE_ID": 66,
      "LAT": 35.83223178380224,
      "LNG": 127.12227501820965,
      "TYPE": "INTERMEDIATE",
      "matched": {
        "id": 3058019000,
        "sub": 0,
        "distance": 35.290920310367014
      }
    },
    {
      "NODE_ID": 67,
      "LAT": 35.832317,
      "LNG": 127.121016,
      "TYPE": "STOP",
      "STOP_ID": 305100883,
      "matched": {
        "id": 3058019000,
        "sub": 0,
        "distance": 35.290920310367014
      }
    },
    {
      "NODE_ID": 68,
      "LAT": 35.83222624591885,
      "LNG": 127.12008977251062,
      "TYPE": "INTERMEDIATE",
      "matched": {
        "id": 3058019000,
        "sub": 0,
        "distance": 35.290920310367014
      }
    },
    {
      "NODE_ID": 69,
      "LAT": 35.83230921,
      "LNG": 127.11764444,
      "TYPE": "STOP",
      "STOP_ID": 305100884,
      "matched": {
        "id": 3058019000,
        "sub": 0,
        "distance": 35.290920310367014
      }
    },
    {
      "NODE_ID": 70,
      "LAT": 35.83223663281885,
      "LNG": 127.11792676985144,
      "TYPE": "INTERMEDIATE",
      "matched": {
        "id": 3058019000,
        "sub": 0,
        "distance": 35.290920310367014
      }
    },
    {
      "NODE_ID": 71,
      "LAT": 35.832197138438275,
      "LNG": 127.11588776158838,
      "TYPE": "INTERMEDIATE",
      "matched": {
        "id": 3058017400,
        "sub": 0,
        "distance": 8.712282045314863
      }
    },
    {
      "NODE_ID": 72,
      "LAT": 35.833914691775554,
      "LNG": 127.11591382102833,
      "TYPE": "INTERMEDIATE",
      "matched": {
        "id": 3058017400,
        "sub": 0,
        "distance": 8.712282045314863
      }
    },
    {
      "NODE_ID": 73,
      "LAT": 35.834778,
      "LNG": 127.116065,
      "TYPE": "STOP",
      "STOP_ID": 305100935,
      "matched": {
        "id": 3058006700,
        "sub": 4,
        "distance": 75.50831554842867
      }
    },
    {
      "NODE_ID": 74,
      "LAT": 35.83566576278518,
      "LNG": 127.11600838621563,
      "TYPE": "INTERMEDIATE",
      "matched": {
        "id": 3058017400,
        "sub": 1,
        "distance": 21.266483672685162
      }
    },
    {
      "NODE_ID": 75,
      "LAT": 35.83570818,
      "LNG": 127.11400487,
      "TYPE": "STOP",
      "STOP_ID": 305100953,
      "matched": {
        "id": 3058017400,
        "sub": 1,
        "distance": 21.266483672685162
      }
    },
    {
      "NODE_ID": 76,
      "LAT": 35.83565446328083,
      "LNG": 127.11380116073587,
      "TYPE": "INTERMEDIATE",
      "matched": {
        "id": 3058017400,
        "sub": 1,
        "distance": 21.266483672685162
      }
    },
    {
      "NODE_ID": 77,
      "LAT": 35.835946897463664,
      "LNG": 127.11219904879316,
      "TYPE": "INTERMEDIATE",
      "matched": {
        "id": 3058017400,
        "sub": 1,
        "distance": 21.266483672685162
      }
    },
    {
      "NODE_ID": 78,
      "LAT": 35.836557,
      "LNG": 127.112353,
      "TYPE": "STOP",
      "STOP_ID": 305100963,
      "matched": {
        "id": 3058017400,
        "sub": 1,
        "distance": 21.266483672685162
      }
    },
    {
      "NODE_ID": 79,
      "LAT": 35.8377275172809,
      "LNG": 127.11221298980395,
      "TYPE": "INTERMEDIATE",
      "matched": {
        "id": 3058017400,
        "sub": 1,
        "distance": 21.266483672685162
      }
    },
    {
      "NODE_ID": 80,
      "LAT": 35.838613489661874,
      "LNG": 127.11045355922487,
      "TYPE": "INTERMEDIATE",
      "matched": {
        "id": 3058017400,
        "sub": 1,
        "distance": 21.266483672685162
      }
    },
    {
      "NODE_ID": 81,
      "LAT": 35.838849,
      "LNG": 127.110153,
      "TYPE": "STOP",
      "STOP_ID": 306132111,
      "matched": {
        "id": 3058017400,
        "sub": 1,
        "distance": 21.266483672685162
      }
    },
    {
      "NODE_ID": 82,
      "LAT": 35.839536416414596,
      "LNG": 127.10888097137816,
      "TYPE": "INTERMEDIATE",
      "matched": {
        "id": 3058008700,
        "sub": 5,
        "distance": 27.953653465003146
      }
    },
    {
      "NODE_ID": 83,
      "LAT": 35.840824219558485,
      "LNG": 127.11034886055715,
      "TYPE": "INTERMEDIATE",
      "matched": {
        "id": 3058008500,
        "sub": 0,
        "distance": 85.80938684985792
      }
    },
    {
      "NODE_ID": 84,
      "LAT": 35.842112464330924,
      "LNG": 127.1096872723169,
      "TYPE": "INTERMEDIATE",
      "matched": {
        "id": 3058008500,
        "sub": 0,
        "distance": 85.80938684985792
      }
    },
    {
      "NODE_ID": 85,
      "LAT": 35.842832,
      "LNG": 127.10944,
      "TYPE": "STOP",
      "STOP_ID": 312132243,
      "matched": {
        "id": 3058008500,
        "sub": 0,
        "distance": 85.80938684985792
      }
    },
    {
      "NODE_ID": 86,
      "LAT": 35.843796023382744,
      "LNG": 127.10925507399244,
      "TYPE": "INTERMEDIATE",
      "matched": {
        "id": 3058008500,
        "sub": 0,
        "distance": 85.80938684985792
      }
    },
    {
      "NODE_ID": 87,
      "LAT": 35.845669,
      "LNG": 127.10922,
      "TYPE": "STOP",
      "STOP_ID": 306032042,
      "matched": {
        "id": 3058008500,
        "sub": 0,
        "distance": 85.80938684985792
      }
    },
    {
      "NODE_ID": 88,
      "LAT": 35.84560176531502,
      "LNG": 127.10915300463728,
      "TYPE": "INTERMEDIATE",
      "matched": {
        "id": 3058008500,
        "sub": 0,
        "distance": 85.80938684985792
      }
    },
    {
      "NODE_ID": 89,
      "LAT": 35.84739852345658,
      "LNG": 127.10905144308987,
      "TYPE": "INTERMEDIATE",
      "matched": {
        "id": 3058008500,
        "sub": 5,
        "distance": 95.58814997734183
      }
    },
    {
      "NODE_ID": 90,
      "LAT": 35.84849720831799,
      "LNG": 127.11026308388554,
      "TYPE": "INTERMEDIATE",
      "matched": {
        "id": 3058008500,
        "sub": 6,
        "distance": 50.002252291810244
      }
    },
    {
      "NODE_ID": 91,
      "LAT": 35.84962907249933,
      "LNG": 127.11192610834047,
      "TYPE": "INTERMEDIATE",
      "matched": {
        "id": 3058008400,
        "sub": 0,
        "distance": 44.49288573494234
      }
    },
    {
      "NODE_ID": 92,
      "LAT": 35.84947405841194,
      "LNG": 127.11349841294843,
      "TYPE": "INTERMEDIATE",
      "matched": {
        "id": 3058008400,
        "sub": 0,
        "distance": 44.49288573494234
      }
    },
    {
      "NODE_ID": 93,
      "LAT": 35.84909503,
      "LNG": 127.11385266,
      "TYPE": "STOP",
      "STOP_ID": 306101107,
      "matched": {
        "id": 3058008400,
        "sub": 0,
        "distance": 44.49288573494234
      }
    },
    {
      "NODE_ID": 94,
      "LAT": 35.84853930845997,
      "LNG": 127.11540718271867,
      "TYPE": "INTERMEDIATE",
      "matched": {
        "id": 3058003800,
        "sub": 2,
        "distance": 15.3751780095381
      }
    },
    {
      "NODE_ID": 95,
      "LAT": 35.84760920900527,
      "LNG": 127.1173064561219,
      "TYPE": "INTERMEDIATE",
      "matched": {
        "id": 3058003800,
        "sub": 2,
        "distance": 15.3751780095381
      }
    },
    {
      "NODE_ID": 96,
      "LAT": 35.84861429936527,
      "LNG": 127.11873833430379,
      "TYPE": "INTERMEDIATE",
      "matched": {
        "id": 3058013100,
        "sub": 1,
        "distance": 94.04565299054538
      }
    },
    {
      "NODE_ID": 97,
      "LAT": 35.84934543,
      "LNG": 127.11968893,
      "TYPE": "STOP",
      "STOP_ID": 306101113,
      "matched": {
        "id": 3058013100,
        "sub": 2,
        "distance": 11.531169025241933
      }
    },
    {
      "NODE_ID": 98,
      "LAT": 35.85009061612447,
      "LNG": 127.11975695937659,
      "TYPE": "INTERMEDIATE",
      "matched": {
        "id": 3058013200,
        "sub": 3,
        "distance": 26.39796109236523
      }
    },
    {
      "NODE_ID": 99,
      "LAT": 35.851806131810264,
      "LNG": 127.11998552540825,
      "TYPE": "INTERMEDIATE",
      "matched": {
        "id": 3058012900,
        "sub": 1,
        "distance": 25.890447389755906
      }
    },
    {
      "NODE_ID": 100,
      "LAT": 35.85361352,
      "LNG": 127.11979367,
      "TYPE": "STOP",
      "STOP_ID": 306101170,
      "matched": {
        "id": 3058012900,
        "sub": 2,
        "distance": 11.779840492651363
      }
    },
    {
      "NODE_ID": 101,
      "LAT": 35.85353921966401,
      "LNG": 127.1197401745406,
      "TYPE": "INTERMEDIATE",
      "matched": {
        "id": 3058012900,
        "sub": 2,
        "distance": 8.123395885801143
      }
    },
    {
      "NODE_ID": 102,
      "LAT": 35.85517805975971,
      "LNG": 127.12009535674257,
      "TYPE": "INTERMEDIATE",
      "matched": {
        "id": 3058012900,
        "sub": 2,
        "distance": 8.123395885801143
      }
    },
    {
      "NODE_ID": 103,
      "LAT": 35.856559,
      "LNG": 127.11982,
      "TYPE": "STOP",
      "STOP_ID": 306101229,
      "matched": {
        "id": 3058013000,
        "sub": 3,
        "distance": 52.17351088188488
      }
    },
    {
      "NODE_ID": 104,
      "LAT": 35.8566006587629,
      "LNG": 127.11984097046825,
      "TYPE": "INTERMEDIATE",
      "matched": {
        "id": 3058013000,
        "sub": 3,
        "distance": 55.34185355963141
      }
    },
    {
      "NODE_ID": 105,
      "LAT": 35.85765191539967,
      "LNG": 127.11834662429186,
      "TYPE": "INTERMEDIATE",
      "matched": {
        "id": 3058008300,
        "sub": 3,
        "distance": 39.32631478714875
      }
    },
    {
      "NODE_ID": 106,
      "LAT": 35.85863312,
      "LNG": 127.11802905,
      "TYPE": "STOP",
      "STOP_ID": 306101250,
      "matched": {
        "id": 3058008400,
        "sub": 3,
        "distance": 62.18451421678603
      }
    },
    {
      "NODE_ID": 107,
      "LAT": 35.859285256407794,
      "LNG": 127.11792289343461,
      "TYPE": "INTERMEDIATE",
      "matched": {
        "id": 3058008400,
        "sub": 5,
        "distance": 41.54380589527019
      }
    },
    {
      "NODE_ID": 108,
      "LAT": 35.86047513761874,
      "LNG": 127.11659667896147,
      "TYPE": "INTERMEDIATE",
      "matched": {
        "id": 3058008300,
        "sub": 6,
        "distance": 2.7142364915409876
      }
    },
    {
      "NODE_ID": 109,
      "LAT": 35.86186461726562,
      "LNG": 127.11543351806566,
      "TYPE": "INTERMEDIATE",
      "matched": {
        "id": 3058008300,
        "sub": 6,
        "distance": 2.7142364915409876
      }
    },
    {
      "NODE_ID": 110,
      "LAT": 35.8630123,
      "LNG": 127.11478688,
      "TYPE": "STOP",
      "STOP_ID": 306101297,
      "matched": {
        "id": 3058008300,
        "sub": 7,
        "distance": 16.42532300286407
      }
    },
    {
      "NODE_ID": 111,
      "LAT": 35.86341667181096,
      "LNG": 127.11467808817332,
      "TYPE": "INTERMEDIATE",
      "matched": {
        "id": 3058008300,
        "sub": 7,
        "distance": 59.27593042055453
      }
    },
    {
      "NODE_ID": 112,
      "LAT": 35.86511478193333,
      "LNG": 127.11457956784724,
      "TYPE": "INTERMEDIATE",
      "matched": {
        "id": 3058008300,
        "sub": 8,
        "distance": 52.024442181654564
      }
    },
    {
      "NODE_ID": 113,
      "LAT": 35.8661518,
      "LNG": 127.11470965,
      "TYPE": "STOP",
      "STOP_ID": 306101341,
      "matched": {
        "id": 3058008300,
        "sub": 9,
        "distance": 41.84031780849166
      }
    },
    {
      "NODE_ID": 114,
      "LAT": 35.86684642083489,
      "LNG": 127.11465749827853,
      "TYPE": "INTERMEDIATE",
      "matched": {
        "id": 3058008300,
        "sub": 9,
        "distance": 35.756327765070914
      }
    },
    {
      "NODE_ID": 115,
      "LAT": 35.86777926379847,
      "LNG": 127.11534444879017,
      "TYPE": "INTERMEDIATE",
      "matched": {
        "id": 3058008300,
        "sub": 10,
        "distance": 75.79020058346318
      }
    },
    {
      "NODE_ID": 116,
      "LAT": 35.867741,
      "LNG": 127.11673,
      "TYPE": "STOP",
      "STOP_ID": 306101357,
      "matched": {
        "id": 3058008300,
        "sub": 10,
        "distance": 75.79020058346318
      }
    },
    {
      "NODE_ID": 117,
      "LAT": 35.86778267049113,
      "LNG": 127.11755282680137,
      "TYPE": "INTERMEDIATE",
      "matched": {
        "id": 3058008300,
        "sub": 10,
        "distance": 75.79020058346318
      }
    },
    {
      "NODE_ID": 118,
      "LAT": 35.867756028754236,
      "LNG": 127.11974991490162,
      "TYPE": "INTERMEDIATE",
      "matched": {
        "id": 3058008300,
        "sub": 10,
        "distance": 75.79020058346318
      }
    },
    {
      "NODE_ID": 119,
      "LAT": 35.868089727223186,
      "LNG": 127.12151698703795,
      "TYPE": "INTERMEDIATE",
      "matched": {
        "id": 3058012900,
        "sub": 6,
        "distance": 7.480412345604279
      }
    },
    {
      "NODE_ID": 120,
      "LAT": 35.86963243271201,
      "LNG": 127.1214643421327,
      "TYPE": "INTERMEDIATE",
      "matched": {
        "id": 3058012900,
        "sub": 6,
        "distance": 7.480412345604279
      }
    },
    {
      "NODE_ID": 121,
      "LAT": 35.86969211459971,
      "LNG": 127.12367149550244,
      "TYPE": "INTERMEDIATE",
      "matched": {
        "id": 3058012900,
        "sub": 6,
        "distance": 7.480412345604279
      }
    },
    {
      "NODE_ID": 122,
      "LAT": 35.86969257385945,
      "LNG": 127.12579044396395,
      "TYPE": "INTERMEDIATE",
      "matched": {
        "id": 3058001200,
        "sub": 1,
        "distance": 40.143806814500344
      }
    },
    {
      "NODE_ID": 123,
      "LAT": 35.8700401094438,
      "LNG": 127.1277156316446,
      "TYPE": "INTERMEDIATE",
      "matched": {
        "id": 3058001100,
        "sub": 1,
        "distance": 24.290552907273213
      }
    },
    {
      "NODE_ID": 124,
      "LAT": 35.871797454738385,
      "LNG": 127.12768411509336,
      "TYPE": "INTERMEDIATE",
      "matched": {
        "id": 3058001100,
        "sub": 1,
        "distance": 24.290552907273213
      }
    },
    {
      "NODE_ID": 125,
      "LAT": 35.8721074,
      "LNG": 127.1277186,
      "TYPE": "STOP",
      "STOP_ID": 305032430,
      "matched": {
        "id": 3058001100,
        "sub": 1,
        "distance": 24.290552907273213
      }
    },
    {
      "NODE_ID": 126,
      "LAT": 35.873427356580976,
      "LNG": 127.1284357014936,
      "TYPE": "INTERMEDIATE",
      "matched": {
        "id": 3058001100,
        "sub": 1,
        "distance": 24.290552907273213
      }
    },
    {
      "NODE_ID": 127,
      "LAT": 35.872757,
      "LNG": 127.130066,
      "TYPE": "STOP",
      "STOP_ID": 305032397,
      "matched": {
        "id": 3058001100,
        "sub": 1,
        "distance": 24.290552907273213
      }
    },
    {
      "NODE_ID": 128,
      "LAT": 35.87264152095998,
      "LNG": 127.1302888130819,
      "TYPE": "INTERMEDIATE",
      "matched": {
        "id": 3058001100,
        "sub": 1,
        "distance": 24.290552907273213
      }
    },
    {
      "NODE_ID": 129,
      "LAT": 35.87173167921179,
      "LNG": 127.13204850641422,
      "TYPE": "INTERMEDIATE",
      "matched": {
        "id": 3058001100,
        "sub": 1,
        "distance": 24.290552907273213
      }
    },
    {
      "NODE_ID": 130,
      "LAT": 35.8725593,
      "LNG": 127.1339642,
      "TYPE": "STOP",
      "STOP_ID": 305032398,
      "matched": {
        "id": 3058001100,
        "sub": 1,
        "distance": 24.290552907273213
      }
    },
    {
      "NODE_ID": 131,
      "LAT": 35.87249693038872,
      "LNG": 127.13389124014691,
      "TYPE": "INTERMEDIATE",
      "matched": {
        "id": 3058001100,
        "sub": 1,
        "distance": 24.290552907273213
      }
    },
    {
      "NODE_ID": 132,
      "LAT": 35.87394072447541,
      "LNG": 127.13515376583143,
      "TYPE": "INTERMEDIATE",
      "matched": {
        "id": 3058001100,
        "sub": 1,
        "distance": 24.290552907273213
      }
    },
    {
      "NODE_ID": 133,
      "LAT": 35.87540018322617,
      "LNG": 127.13632642133156,
      "TYPE": "INTERMEDIATE",
      "matched": {
        "id": 3058001100,
        "sub": 1,
        "distance": 24.290552907273213
      }
    },
    {
      "NODE_ID": 134,
      "LAT": 35.87688947873087,
      "LNG": 127.13548290744566,
      "TYPE": "INTERMEDIATE",
      "matched": {
        "id": 3058001100,
        "sub": 1,
        "distance": 24.290552907273213
      }
    },
    {
      "NODE_ID": 135,
      "LAT": 35.876991,
      "LNG": 127.135157,
      "TYPE": "STOP",
      "STOP_ID": 305032400,
      "matched": {
        "id": 3058001100,
        "sub": 1,
        "distance": 24.290552907273213
      }
    },
    {
      "NODE_ID": 136,
      "LAT": 35.878247,
      "LNG": 127.133709,
      "TYPE": "STOP",
      "STOP_ID": 305032528,
      "matched": {
        "id": 3058001100,
        "sub": 1,
        "distance": 24.290552907273213
      }
    },
    {
      "NODE_ID": 137,
      "LAT": 35.878177134758445,
      "LNG": 127.1339337896492,
      "TYPE": "INTERMEDIATE",
      "matched": {
        "id": 3058001100,
        "sub": 1,
        "distance": 24.290552907273213
      }
    },
    {
      "NODE_ID": 138,
      "LAT": 35.879235214418586,
      "LNG": 127.13220800461913,
      "TYPE": "INTERMEDIATE",
      "matched": {
        "id": 3058001100,
        "sub": 1,
        "distance": 24.290552907273213
      }
    },
    {
      "NODE_ID": 139,
      "LAT": 35.879291,
      "LNG": 127.130474,
      "TYPE": "STOP",
      "STOP_ID": 305032401,
      "matched": {
        "id": 3058001100,
        "sub": 1,
        "distance": 24.290552907273213
      }
    },
    {
      "NODE_ID": 140,
      "LAT": 35.87924483076056,
      "LNG": 127.13006096832214,
      "TYPE": "INTERMEDIATE",
      "matched": {
        "id": 3058001100,
        "sub": 1,
        "distance": 24.290552907273213
      }
    },
    {
      "NODE_ID": 141,
      "LAT": 35.87901951765294,
      "LNG": 127.12791094999211,
      "TYPE": "INTERMEDIATE",
      "matched": {
        "id": 3058031800,
        "sub": 6,
        "distance": 6.379613058702726
      }
    },
    {
      "NODE_ID": 142,
      "LAT": 35.87734429194812,
      "LNG": 127.12735922630397,
      "TYPE": "INTERMEDIATE",
      "matched": {
        "id": 3058031800,
        "sub": 6,
        "distance": 6.379613058702726
      }
    },
    {
      "NODE_ID": 143,
      "LAT": 35.87580987929317,
      "LNG": 127.12632785282513,
      "TYPE": "INTERMEDIATE",
      "matched": {
        "id": 3058031700,
        "sub": 4,
        "distance": 32.41815340209764
      }
    },
    {
      "NODE_ID": 144,
      "LAT": 35.875561,
      "LNG": 127.125978,
      "TYPE": "STOP",
      "STOP_ID": 306101413,
      "matched": {
        "id": 3058031700,
        "sub": 4,
        "distance": 71.44091359861804
      }
    },
    {
      "NODE_ID": 145,
      "LAT": 35.874478162802546,
      "LNG": 127.12481936233456,
      "TYPE": "INTERMEDIATE",
      "matched": {
        "id": 3058031700,
        "sub": 4,
        "distance": 71.44091359861804
      }
    },
    {
      "NODE_ID": 146,
      "LAT": 35.87374,
      "LNG": 127.123892,
      "TYPE": "STOP",
      "STOP_ID": 305032442,
      "matched": {
        "id": 3058031700,
        "sub": 4,
        "distance": 71.44091359861804
      }
    },
    {
      "NODE_ID": 147,
      "LAT": 35.87316275344205,
      "LNG": 127.12332259230696,
      "TYPE": "INTERMEDIATE",
      "matched": {
        "id": 3058031800,
        "sub": 3,
        "distance": 7.365252676516344
      }
    },
    {
      "NODE_ID": 148,
      "LAT": 35.87189359190407,
      "LNG": 127.12178408379688,
      "TYPE": "INTERMEDIATE",
      "matched": {
        "id": 3058031800,
        "sub": 3,
        "distance": 7.365252676516344
      }
    },
    {
      "NODE_ID": 149,
      "LAT": 35.87029302698508,
      "LNG": 127.12119810121895,
      "TYPE": "INTERMEDIATE",
      "matched": {
        "id": 3058031800,
        "sub": 1,
        "distance": 41.90196243588667
      }
    },
    {
      "NODE_ID": 150,
      "LAT": 35.86975383482614,
      "LNG": 127.11993721527766,
      "TYPE": "INTERMEDIATE",
      "matched": {
        "id": 3058031800,
        "sub": 1,
        "distance": 41.90196243588667
      }
    },
    {
      "NODE_ID": 151,
      "LAT": 35.8699127,
      "LNG": 127.1184873,
      "TYPE": "STOP",
      "STOP_ID": 306032307,
      "matched": {
        "id": 3058031800,
        "sub": 1,
        "distance": 41.90196243588667
      }
    },
    {
      "NODE_ID": 152,
      "LAT": 35.869755971628784,
      "LNG": 127.117762106173,
      "TYPE": "INTERMEDIATE",
      "matched": {
        "id": 3058031800,
        "sub": 1,
        "distance": 41.90196243588667
      }
    },
    {
      "NODE_ID": 153,
      "LAT": 35.86980321849705,
      "LNG": 127.11554328609617,
      "TYPE": "INTERMEDIATE",
      "matched": {
        "id": 3058000700,
        "sub": 0,
        "distance": 51.9036339131638
      }
    },
    {
      "NODE_ID": 154,
      "LAT": 35.869941,
      "LNG": 127.114241,
      "TYPE": "STOP",
      "STOP_ID": 306032306,
      "matched": {
        "id": 3058008400,
        "sub": 11,
        "distance": 53.75734007856709
      }
    },
    {
      "NODE_ID": 155,
      "LAT": 35.86996016327779,
      "LNG": 127.11340791133604,
      "TYPE": "INTERMEDIATE",
      "matched": {
        "id": 3058008400,
        "sub": 11,
        "distance": 53.75734007856709
      }
    },
    {
      "NODE_ID": 156,
      "LAT": 35.87003828171669,
      "LNG": 127.11119041409411,
      "TYPE": "INTERMEDIATE",
      "matched": {
        "id": 3058008400,
        "sub": 11,
        "distance": 53.75734007856709
      }
    },
    {
      "NODE_ID": 157,
      "LAT": 35.8697397,
      "LNG": 127.109252,
      "TYPE": "STOP",
      "STOP_ID": 306032304,
      "matched": {
        "id": 3058008400,
        "sub": 11,
        "distance": 53.75734007856709
      }
    },
    {
      "NODE_ID": 158,
      "LAT": 35.86978991758047,
      "LNG": 127.10901947360558,
      "TYPE": "INTERMEDIATE",
      "matched": {
        "id": 3058008400,
        "sub": 11,
        "distance": 53.75734007856709
      }
    }
  ]
}